sfzlint/__init__.py
sfzlint/cli.py
sfzlint/errors.py
sfzlint/headers.py
sfzlint/lint.py
sfzlint/opcodes.py
sfzlint/parser.py
sfzlint/settings.py
sfzlint/sfz.lark
sfzlint/spec.py
sfzlint/syntax.yml
sfzlint/validators.py
sfzlint-0.1.4.dist-info/LICENSE
sfzlint-0.1.4.dist-info/METADATA
sfzlint-0.1.4.dist-info/WHEEL
sfzlint-0.1.4.dist-info/entry_points.txt
sfzlint-0.1.4.dist-info/top_level.txt
sfzlint-0.1.4.dist-info/RECORD
