Metadata-Version: 2.1
Name: sfzlint
Version: 0.1.4
Summary: parser and linter for sfz files written in python
Home-page: https://github.com/jisaacstone/sfzlint
Author: jisaacstone
License: MIT
Project-URL: Bug Tracker, https://github.com/jisaacstone/sfzlint/issues
Platform: UNKNOWN
Requires-Python: >3.6
License-File: LICENSE
Requires-Dist: appdirs
Requires-Dist: lark-parser (>=0.7.8)
Requires-Dist: pyyaml (>=6.0.0)
